identify_browser/__init__.py
identify_browser-1.0.0.dist-info/LICENSE
identify_browser-1.0.0.dist-info/METADATA
identify_browser-1.0.0.dist-info/WHEEL
identify_browser-1.0.0.dist-info/top_level.txt
identify_browser-1.0.0.dist-info/RECORD
