Metadata-Version: 2.1
Name: identify_browser
Version: 1.0.0
Summary: A function that accepts a user agent string (and, optionally, Sec-CH-UA and Sec-CH-UA-Platform headers) and returns its best guess at the browser name, version, and platform.
Author-email: Adam Taylor <ataylor32@gmail.com>
Project-URL: Homepage, https://github.com/ataylor32/python-identify_browser
Project-URL: Repository, https://github.com/ataylor32/python-identify_browser.git
Project-URL: Issues, https://github.com/ataylor32/python-identify_browser/issues
Project-URL: Changelog, https://github.com/ataylor32/python-identify_browser/blob/master/CHANGELOG.rst
Classifier: Development Status :: 5 - Production/Stable
Classifier: Programming Language :: Python :: 3
Classifier: Programming Language :: Python :: 3.8
Classifier: Programming Language :: Python :: 3.9
Classifier: Programming Language :: Python :: 3.10
Classifier: Programming Language :: Python :: 3.11
Classifier: Programming Language :: Python :: 3.12
Classifier: License :: OSI Approved :: MIT License
Classifier: Operating System :: OS Independent
License-File: LICENSE
Requires-Dist: ua-parser >=0.18.0
